app/__init__.py
app/main.py
app/pyinstaller.py
m3u_prsr-0.1.33.dist-info/LICENSE
m3u_prsr-0.1.33.dist-info/METADATA
m3u_prsr-0.1.33.dist-info/WHEEL
m3u_prsr-0.1.33.dist-info/entry_points.txt
m3u_prsr-0.1.33.dist-info/RECORD
