Metadata-Version: 2.1
Name: m3u-prsr
Version: 0.1.33
Summary: 
Home-page: https://github.com/pythoninthegrass/m3u_prsr/
License: Unlicense
Author: Dave A
Author-email: dave@dvndrsn.com
Requires-Python: >=3.11,<3.13
Classifier: License :: OSI Approved
Classifier: Programming Language :: Python :: 3
Classifier: Programming Language :: Python :: 3.11
Project-URL: Repository, https://github.com/pythoninthegrass/m3u_prsr/
